<?xml version="1.0" encoding="UTF-8" ?>
<!DOCTYPE mapper
        PUBLIC "-//mybatis.org//DTD Mapper 3.0//EN"
        "http://mybatis.org/dtd/mybatis-3-mapper.dtd">

<mapper namespace="com.htcsweb.dao.OdBlastInspectionProcessDao">


    <select id="getAllByLike" resultType="map">
        Select pro.project_name,s.status_name,p.contract_no,p.grade,p.od,p.wt,p.p_length,p.weight,p.heat_no,o.*
        from od_blast_inspection_process o
        left join pipe_basic_info p on p.pipe_no=o.pipe_no
        left join contract_info c on p.contract_no=c.contract_no
        left join project_info pro on c.project_no=pro.project_no
        left join pipe_status s on s.status_code=p.status
        <where>
            <if test="pipe_no!=null and pipe_no!=''">
                AND o.pipe_no LIKE CONCAT('%',#{pipe_no},'%')
            </if>
            <if test="operator_no!=null and operator_no!=''">
                AND o.operator_no LIKE CONCAT('%',#{operator_no},'%')
            </if>
            <if test="mill_no!=null and mill_no!=''">
                AND o.mill_no =#{mill_no}
            </if>
            <if test="begin_time!=null">
                <![CDATA[ AND DATE_FORMAT(o.operation_time,'%Y-%m-%d %H:%T:%s')>=DATE_FORMAT(#{begin_time},'%Y-%m-%d 00:00:00')]]>
            </if>
            <if test="end_time!=null">
                <![CDATA[ AND DATE_FORMAT(o.operation_time,'%Y-%m-%d %H:%T:%s')<DATE_FORMAT(DATE_ADD(#{end_time},INTERVAL 1 DAY),'%Y-%m-%d 00:00:00')]]>
            </if>
        </where>
        ORDER BY o.id DESC
        limit #{skip},#{take}
    </select>


    <select id="getCountAllByLike" resultType="int">
        select count(*) from od_blast_inspection_process o
        left join pipe_basic_info p on p.pipe_no=o.pipe_no
        left join contract_info c on p.contract_no=c.contract_no
        left join project_info pro on c.project_no=pro.project_no
        left join pipe_status s on s.status_code=p.status
        <where>
            <if test="pipe_no!=null and pipe_no!=''">
                AND o.pipe_no LIKE CONCAT('%',#{pipe_no},'%')
            </if>
            <if test="operator_no!=null and operator_no!=''">
                AND o.operator_no LIKE CONCAT('%',#{operator_no},'%')
            </if>
            <if test="mill_no!=null and mill_no!=''">
                AND o.mill_no =#{mill_no}
            </if>
            <if test="begin_time!=null">
                <![CDATA[ AND DATE_FORMAT(o.operation_time,'%Y-%m-%d %H:%T:%s')>=DATE_FORMAT(#{begin_time},'%Y-%m-%d 00:00:00')]]>
            </if>
            <if test="end_time!=null">
                <![CDATA[ AND DATE_FORMAT(o.operation_time,'%Y-%m-%d %H:%T:%s')<DATE_FORMAT(DATE_ADD(#{end_time},INTERVAL 1 DAY),'%Y-%m-%d 00:00:00')]]>
            </if>
        </where>

    </select>


    <insert id="addOdBlastInProcess" parameterType="com.htcsweb.entity.OdBlastInspectionProcess">
        INSERT INTO od_blast_inspection_process(pipe_no,operation_time,operator_no,air_temp,relative_humidity,dew_point,blast_finish_sa25,profile,surface_dust_rating,pipe_temp,salt_contamination_after_blasting,surface_condition,upload_files,remark,result,mill_no,oil_water_in_air_compressor,elapsed_time) VALUES (#{pipe_no},#{operation_time},#{operator_no},#{air_temp},#{relative_humidity},#{dew_point},#{blast_finish_sa25},#{profile},#{surface_dust_rating},#{pipe_temp},#{salt_contamination_after_blasting},#{surface_condition},#{upload_files},#{remark},#{result},#{mill_no},#{oil_water_in_air_compressor},#{elapsed_time})
    </insert>

    <select id="getOdBlastInProcess" resultType="com.htcsweb.entity.OdBlastInspectionProcess">
        SELECT * from od_blast_inspection_process
    </select>

    <update id="updateOdBlastInProcess" parameterType="com.htcsweb.entity.OdBlastInspectionProcess">
        UPDATE od_blast_inspection_process set pipe_no=#{pipe_no},operation_time=#{operation_time},operator_no=#{operator_no},air_temp=#{air_temp},relative_humidity=#{relative_humidity},dew_point=#{dew_point},blast_finish_sa25=#{blast_finish_sa25},profile=#{profile},surface_dust_rating=#{surface_dust_rating},pipe_temp=#{pipe_temp},salt_contamination_after_blasting=#{salt_contamination_after_blasting},surface_condition=#{surface_condition},upload_files=#{upload_files},remark=#{remark},result=#{result},mill_no=#{mill_no},oil_water_in_air_compressor=#{oil_water_in_air_compressor},elapsed_time=#{elapsed_time} where id=#{id}
    </update>


    <select id="getCount" resultType="int">
        select count(*) from od_blast_inspection_process
    </select>

    <resultMap id="all" type="com.htcsweb.entity.OdBlastInspectionProcess">
        <id property="id" column="id"></id>
        <result property="pipe_no" column="pipe_no"></result>
        <result property="operation_time" column="operation_time"></result>
        <result property="operator_no" column="operator_no"></result>
        <result property="air_temp" column="air_temp"></result>
        <result property="relative_humidity" column="relative_humidity"></result>
        <result property="dew_point" column="dew_point"></result>
        <result property="blast_finish_sa25" column="blast_finish_sa25"></result>
        <result property="profile" column="profile"></result>
        <result property="surface_dust_rating" column="surface_dust_rating"></result>
        <result property="pipe_temp" column="pipe_temp"></result>
        <result property="salt_contamination_after_blasting" column="salt_contamination_after_blasting"></result>
        <result property="surface_condition" column="surface_condition"></result>
        <result property="upload_files" column="upload_files"></result>
        <result property="remark" column="remark"></result>
        <result property="result" column="result"></result>
        <result property="mill_no" column="mill_no"></result>
        <result property="oil_water_in_air_compressor" column="oil_water_in_air_compressor"></result>
    </resultMap>

    <select id="feny"  resultMap="all">
        select * from od_blast_inspection_process where id limit #{arg0},#{arg1}
    </select>

    <select id="getOdBlastInProcessById" parameterType="int" resultType="com.htcsweb.entity.OdBlastInspectionProcess">
        select * from od_blast_inspection_process where id=#{id}
    </select>

    <delete id="delOdBlastInspectionProcess">
        delete from od_blast_inspection_process WHERE
        <foreach collection="array" item="item" open="id in (" separator="," close=")">
            #{item}
        </foreach>
    </delete>
    <!--获取当天外打砂检验记录-->
    <select id="getOdBlastInspectionRecord" resultType="map">
        Select  o.*
        from od_blast_inspection_process o
        left join pipe_basic_info p on p.pipe_no=o.pipe_no
        left join contract_info c on p.contract_no=c.contract_no
        left join project_info pro on c.project_no=pro.project_no
        <where>
            <if test="project_no!=null and project_no!=''">
                pro.project_no=#{project_no}
            </if>
            <if test="mill_no!=null and mill_no!=''">
                AND o.mill_no=#{mill_no}
            </if>
            <if test="external_coating!=null and external_coating!=''">
                AND c.external_coating=#{external_coating}
            </if>
            AND format(c.od,3)=format(#{od},3)
            AND format(c.wt,3)=format(#{wt},3)
            <if test="begin_time!=null">
                <![CDATA[ AND DATE_FORMAT(o.operation_time,'%Y-%m-%d %H:%i:%s')>=DATE_FORMAT(#{begin_time},'%Y-%m-%d %H:%i:%s')]]>
            </if>
            <if test="end_time!=null">
                <![CDATA[ AND DATE_FORMAT(o.operation_time,'%Y-%m-%d %H:%i:%s')<DATE_FORMAT(#{end_time},'%Y-%m-%d %H:%i:%s')]]>
            </if>
        </where>
        ORDER BY o.id DESC
    </select>
    <!--更新等待时间-->
    <!--<update id="updateElapsedTime">-->
        <!--update od_blast_inspection_process set elapsed_time=(TIMESTAMPDIFF(MINUTE ,#{begin_time},#{end_time})) where id=#{id}-->
    <!--</update>-->
    <update id="updateElapsedTime">
      update od_blast_inspection_process set elapsed_time=#{elapsed_time} where id=#{id}
    </update>
    <!--根据外涂时间得到对应的外打砂检验时间 获取id-->
    <select id="getOdBlastInfoBy2fbeCoatingInfo" resultType="map">
         select ob.id,oc.operation_time as odcoatingtime,ob.operation_time as odblasttime  from od_blast_inspection_process ob inner join od_coating_2fbe_process oc on ob.pipe_no=oc.pipe_no
         where   oc.operation_time >=ob.operation_time
         AND ob.pipe_no=#{pipe_no} and oc.id=#{id}
         order by ob.operation_time desc
         limit 1
    </select>
    <select id="getOdBlastInfoBy3lpeCoatingInfo" resultType="map">
        select ob.id,oc.operation_time as odcoatingtime,ob.operation_time as odblasttime  from od_blast_inspection_process ob inner join od_coating_3lpe_process oc on ob.pipe_no=oc.pipe_no
        where   oc.operation_time >=ob.operation_time
        AND ob.pipe_no=#{pipe_no} and oc.id=#{id}
        order by ob.operation_time desc
        limit 1
    </select>
</mapper>